{
	"scriptInfo": {
		"title": "Medal Modifier",
		"author": "StackZ",
		"description": "Modifies the Medal amount.",
		"type": "Player"
	},
	"scriptContent": [{
		"info": {
			"title": "Player 1: 0 Medals",
			"author": "StackZ",
			"description": "Set 0 Medals to player 1."
		},
		"script": [{
			"type": "Medals",
			"player": 1,
			"amount": 0
		}]
	},
	{
		"info": {
			"title": "Player 1: 9999 Medals",
			"author": "StackZ",
			"description": "Set 9999 Medals to player 1."
		},
		"script": [{
			"type": "Medals",
			"player": 1,
			"amount": 9999
		}]
	},
	{
		"info": {
			"title": "Player 2: 0 Medals",
			"author": "StackZ",
			"description": "Set 0 Medals to player 2."
		},
		"script": [{
			"type": "Medals",
			"player": 2,
			"amount": 0
		}]
	},
	{
		"info": {
			"title": "Player 2: 9999 Medals",
			"author": "StackZ",
			"description": "Set 9999 Medals to player 2."
		},
		"script": [{
			"type": "Medals",
			"player": 2,
			"amount": 9999
		}]
	},
	{
		"info": {
			"title": "Player 3: 0 Medals",
			"author": "StackZ",
			"description": "Set 0 Medals to player 3."
		},
		"script": [{
			"type": "Medals",
			"player": 3,
			"amount": 0
		}]
	},
	{
		"info": {
			"title": "Player 3: 9999 Medals",
			"author": "StackZ",
			"description": "Set 9999 Medals to player 3."
		},
		"script": [{
			"type": "Medals",
			"player": 3,
			"amount": 9999
		}]
	},
	{
		"info": {
			"title": "Player 4: 0 Medals",
			"author": "StackZ",
			"description": "Set 0 Medals to player 4."
		},
		"script": [{
			"type": "Medals",
			"player": 4,
			"amount": 0
		}]
	},
	{
		"info": {
			"title": "Player 4: 9999 Medals",
			"author": "StackZ",
			"description": "Set 9999 Medals to player 4."
		},
		"script": [{
			"type": "Medals",
			"player": 4,
			"amount": 9999
		}]
	}
]}